CHANGES
LICENSE
MANIFEST.in
README.rst
requirements.pip
setup.py
test-requirements.pip
android2po/__init__.py
android2po/commands.py
android2po/config.py
android2po/convert.py
android2po/env.py
android2po/program.py
android2po/utils.py
android2po.egg-info/PKG-INFO
android2po.egg-info/SOURCES.txt
android2po.egg-info/dependency_links.txt
android2po.egg-info/entry_points.txt
android2po.egg-info/not-zip-safe
android2po.egg-info/requires.txt
android2po.egg-info/top_level.txt
scripts/a2po
tests/__init__.py
tests/__init__.pyc
tests/helpers.py
tests/helpers.pyc
tests/test_commands.py
tests/test_config.py
tests/test_environment.py
tests/test_language.py
tests/test_options.py
tests/__pycache__/__init__.cpython-37.pyc
tests/__pycache__/helpers.cpython-37.pyc
tests/__pycache__/test_commands.cpython-27-PYTEST.pyc
tests/__pycache__/test_commands.cpython-37-pytest-5.3.2.pyc
tests/__pycache__/test_commands.cpython-37.pyc
tests/__pycache__/test_config.cpython-27-PYTEST.pyc
tests/__pycache__/test_config.cpython-37-pytest-5.3.2.pyc
tests/__pycache__/test_config.cpython-37.pyc
tests/__pycache__/test_environment.cpython-27-PYTEST.pyc
tests/__pycache__/test_environment.cpython-37-pytest-5.3.2.pyc
tests/__pycache__/test_environment.cpython-37.pyc
tests/__pycache__/test_language.cpython-27-PYTEST.pyc
tests/__pycache__/test_language.cpython-37-pytest-5.3.2.pyc
tests/__pycache__/test_language.cpython-37.pyc
tests/__pycache__/test_options.cpython-27-PYTEST.pyc
tests/__pycache__/test_options.cpython-37-pytest-5.3.2.pyc
tests/__pycache__/test_options.cpython-37.pyc
tests/convert/__init__.py
tests/convert/__init__.pyc
tests/convert/test_plurals.py
tests/convert/test_read_write_xml.py
tests/convert/test_special.py
tests/convert/test_string_arrays.py
tests/convert/test_text.py
tests/convert/__pycache__/__init__.cpython-37.pyc
tests/convert/__pycache__/test_plurals.cpython-27-PYTEST.pyc
tests/convert/__pycache__/test_plurals.cpython-37-pytest-5.3.2.pyc
tests/convert/__pycache__/test_plurals.cpython-37.pyc
tests/convert/__pycache__/test_read_write_xml.cpython-27-PYTEST.pyc
tests/convert/__pycache__/test_read_write_xml.cpython-37-pytest-5.3.2.pyc
tests/convert/__pycache__/test_read_write_xml.cpython-37.pyc
