Metadata-Version: 1.1
Name: android2po
Version: 1.6.0
Summary: Convert between Android string resources and gettext .po files.
Home-page: http://github.com/miracle2k/android2po
Author: Michael Elsdoerfer
Author-email: michael@elsdoerfer.com
License: BSD
Platform: UNKNOWN
Classifier: Intended Audience :: Developers
Classifier: License :: OSI Approved :: BSD License
Classifier: Topic :: Software Development :: Localization
